mapped/__init__.py
mapped/basemap.py
mapped/caching.py
mapped/density.py
mapped/dotdensity.py
mapped/example_data.py
mapped/gdf_viewer.py
mapped/omx_viewer.py
mapped/plotly.py
mapped/simple.py
mapped/sources.py
mapped-20.4.2.dist-info/LICENSE
mapped-20.4.2.dist-info/METADATA
mapped-20.4.2.dist-info/WHEEL
mapped-20.4.2.dist-info/top_level.txt
mapped-20.4.2.dist-info/RECORD
