Metadata-Version: 2.1
Name: mapped
Version: 20.4.2
Summary: Simplification layer for generating pretty maps using geopandas and matplotlib or plotly
Home-page: https://github.com/jpn--/mapped
Author: Jeffrey Newman
Author-email: jeff@newman.me
License: GPLv3
Keywords: geopandas,matplotlib,maps,plotly
Platform: UNKNOWN
Classifier: Programming Language :: Python :: 3.7
Requires-Dist: geopandas (>=0.5)
Requires-Dist: matplotlib (>=3.0)
Requires-Dist: contextily (>=1.0rc2)
Requires-Dist: appdirs
Requires-Dist: joblib
Requires-Dist: requests
Requires-Dist: plotly (>=4.1)
